lowpy/__init__.py
lowpy/metrics.py
lowpy/wrapper.py
lowpy-0.4.3.dist-info/LICENSE
lowpy-0.4.3.dist-info/METADATA
lowpy-0.4.3.dist-info/WHEEL
lowpy-0.4.3.dist-info/top_level.txt
lowpy-0.4.3.dist-info/RECORD
