Metadata-Version: 2.1
Name: lowpy
Version: 0.4.3
Summary: High level GPU simulations of low level device characteristics in ML algorithms
Home-page: https://github.com/fordaj/lowpy
Author: Andrew Ford
Author-email: author@example.com
License: UNKNOWN
Platform: UNKNOWN
Classifier: Programming Language :: Python :: 3
Classifier: License :: OSI Approved :: MIT License
Classifier: Operating System :: OS Independent
Requires-Python: >=3.6
